aiidalab/__init__.py
aiidalab/__main__.py
aiidalab/app.py
aiidalab/config.py
aiidalab/environment.py
aiidalab/fetch.py
aiidalab/git_util.py
aiidalab/metadata.py
aiidalab/utils.py
aiidalab/registry/__init__.py
aiidalab/registry/api.py
aiidalab/registry/apps_index.py
aiidalab/registry/core.py
aiidalab/registry/html.py
aiidalab/registry/releases.py
aiidalab/registry/util.py
aiidalab/registry/web.py
aiidalab/registry/yaml.py
aiidalab/registry/schemas/app.schema.json
aiidalab/registry/schemas/apps.schema.json
aiidalab/registry/schemas/apps_index.schema.json
aiidalab/registry/schemas/categories.schema.json
aiidalab/registry/schemas/environment.schema.json
aiidalab/registry/schemas/metadata.schema.json
aiidalab/registry/static/api/openapi-v1.yaml
aiidalab/registry/static/static/favicon.png
aiidalab/registry/static/static/gotobutton.svg
aiidalab/registry/static/static/css/style.css
aiidalab/registry/static/static/img/aiidalab_stacked.png
aiidalab/registry/static/static/img/aiidalab_wide.png
aiidalab/registry/templates/app_page.html
aiidalab/registry/templates/app_page_base.html
aiidalab/registry/templates/base.html
aiidalab/registry/templates/index.html
aiidalab/registry/templates/index_base.html
aiidalab/registry/templates/layout.html
aiidalab-24.9.0.dist-info/LICENSE
aiidalab-24.9.0.dist-info/METADATA
aiidalab-24.9.0.dist-info/WHEEL
aiidalab-24.9.0.dist-info/entry_points.txt
aiidalab-24.9.0.dist-info/top_level.txt
aiidalab-24.9.0.dist-info/RECORD
