Metadata-Version: 2.1
Name: aiidalab
Version: 24.9.0
Summary: Implements core functions of AiiDAlab.
Home-page: https://github.com/aiidalab/aiidalab
Author: The AiiDAlab team
Author-email: aiidalab@materialscloud.org
License: MIT
Classifier: Development Status :: 5 - Production/Stable
Classifier: Framework :: AiiDA
Classifier: License :: OSI Approved :: MIT License
Classifier: Programming Language :: Python :: 3
Classifier: Programming Language :: Python :: 3 :: Only
Classifier: Programming Language :: Python :: Implementation :: CPython
Requires-Python: >=3.9
License-File: LICENSE
Requires-Dist: cachetools ~=4.1
Requires-Dist: click <9,>=7.0
Requires-Dist: click-spinner ~=0.1
Requires-Dist: dulwich ~=0.20
Requires-Dist: packaging >=20.1
Requires-Dist: pip
Requires-Dist: requests ~=2.27
Requires-Dist: requests-cache ~=1.0
Requires-Dist: setuptools
Requires-Dist: tabulate ~=0.8
Requires-Dist: toml ~=0.10
Requires-Dist: traitlets ~=5.0
Requires-Dist: watchdog ~=4.0
Provides-Extra: dev
Requires-Dist: bumpver >=2021.1114 ; extra == 'dev'
Requires-Dist: pre-commit >=3.5 ; extra == 'dev'
Requires-Dist: pytest ~=8.2.0 ; extra == 'dev'
Requires-Dist: pytest-cov ~=5.0 ; extra == 'dev'
Requires-Dist: ruamel.yaml ~=0.16 ; extra == 'dev'
Provides-Extra: docs
Requires-Dist: pydata-sphinx-theme ~=0.13.3 ; extra == 'docs'
Requires-Dist: sphinx ~=4.4.0 ; extra == 'docs'
Requires-Dist: sphinx-panels ~=0.6.0 ; extra == 'docs'
Requires-Dist: sphinxcontrib-contentui ; extra == 'docs'
Requires-Dist: sphinxcontrib-applehelp ==1.0.4 ; extra == 'docs'
Requires-Dist: sphinxcontrib-devhelp ==1.0.2 ; extra == 'docs'
Requires-Dist: sphinxcontrib-htmlhelp ==2.0.1 ; extra == 'docs'
Requires-Dist: sphinxcontrib-qthelp ==1.0.3 ; extra == 'docs'
Requires-Dist: sphinxcontrib-serializinghtml ==1.1.5 ; extra == 'docs'
Requires-Dist: sphinxcontrib-details-directive ; (python_version >= "3.0") and extra == 'docs'
Provides-Extra: registry
Requires-Dist: CacheControl ~=0.12 ; extra == 'registry'
Requires-Dist: jsonref ~=0.2 ; extra == 'registry'
Requires-Dist: jsonschema[format] ~=3.2 ; extra == 'registry'
Requires-Dist: Jinja2 ~=3.0 ; extra == 'registry'
Requires-Dist: requests-mock ~=1.8 ; extra == 'registry'
Requires-Dist: ruamel.yaml ~=0.16 ; extra == 'registry'
